AUTHORS.txt
CHANGES.txt
LICENSE.txt
MANIFEST.in
README.md
setup.py
sqlalchemy_boolean_search.py
SQLAlchemy_boolean_search.egg-info/PKG-INFO
SQLAlchemy_boolean_search.egg-info/SOURCES.txt
SQLAlchemy_boolean_search.egg-info/dependency_links.txt
SQLAlchemy_boolean_search.egg-info/not-zip-safe
SQLAlchemy_boolean_search.egg-info/requires.txt
SQLAlchemy_boolean_search.egg-info/top_level.txt