Metadata-Version: 1.1
Name: SQLAlchemy-boolean-search
Version: 0.1.1
Summary: Boolean search expression parser for SQLAlchemy
Home-page: http://github.com/lingthio/SQLAlchemy-boolean-search
Author: Ling Thio
Author-email: ling.thio@gmail.com
License: BSD License
Keywords: Boolean search Flask SQLAlchemy
Platform: any
Classifier: Development Status :: 4 - Beta
Classifier: Environment :: Web Environment
Classifier: Framework :: Flask
Classifier: Intended Audience :: Developers
Classifier: License :: OSI Approved :: BSD License
Classifier: Natural Language :: English
Classifier: Operating System :: OS Independent
Classifier: Programming Language :: Python
Classifier: Programming Language :: Python :: 2.6
Classifier: Programming Language :: Python :: 2.7
Classifier: Programming Language :: Python :: 3.3
Classifier: Programming Language :: Python :: 3.4
Classifier: Topic :: Database :: Front-Ends
Classifier: Topic :: Software Development :: Libraries :: Python Modules
